awslimitchecker/__init__.py
awslimitchecker/checker.py
awslimitchecker/connectable.py
awslimitchecker/limit.py
awslimitchecker/quotas.py
awslimitchecker/runner.py
awslimitchecker/trustedadvisor.py
awslimitchecker/utils.py
awslimitchecker/version.py
awslimitchecker/alerts/__init__.py
awslimitchecker/alerts/base.py
awslimitchecker/alerts/dummy.py
awslimitchecker/alerts/pagerdutyv1.py
awslimitchecker/metrics/__init__.py
awslimitchecker/metrics/base.py
awslimitchecker/metrics/datadog.py
awslimitchecker/metrics/dummy.py
awslimitchecker/services/__init__.py
awslimitchecker/services/apigateway.py
awslimitchecker/services/autoscaling.py
awslimitchecker/services/base.py
awslimitchecker/services/certificatemanager.py
awslimitchecker/services/cloudformation.py
awslimitchecker/services/cloudfront.py
awslimitchecker/services/cloudtrail.py
awslimitchecker/services/directoryservice.py
awslimitchecker/services/dynamodb.py
awslimitchecker/services/ebs.py
awslimitchecker/services/ec2.py
awslimitchecker/services/ecs.py
awslimitchecker/services/efs.py
awslimitchecker/services/eks.py
awslimitchecker/services/elasticache.py
awslimitchecker/services/elasticbeanstalk.py
awslimitchecker/services/elb.py
awslimitchecker/services/firehose.py
awslimitchecker/services/iam.py
awslimitchecker/services/kinesis.py
awslimitchecker/services/lambdafunc.py
awslimitchecker/services/rds.py
awslimitchecker/services/redshift.py
awslimitchecker/services/route53.py
awslimitchecker/services/s3.py
awslimitchecker/services/ses.py
awslimitchecker/services/vpc.py
awslimitchecker/tests/__init__.py
awslimitchecker/tests/conftest.py
awslimitchecker/tests/support.py
awslimitchecker/tests/test_checker.py
awslimitchecker/tests/test_connectable.py
awslimitchecker/tests/test_integration.py
awslimitchecker/tests/test_limit.py
awslimitchecker/tests/test_quotas.py
awslimitchecker/tests/test_runner.py
awslimitchecker/tests/test_trustedadvisor.py
awslimitchecker/tests/test_utils.py
awslimitchecker/tests/test_version.py
awslimitchecker-12.0.0.dist-info/LICENSE
awslimitchecker-12.0.0.dist-info/METADATA
awslimitchecker-12.0.0.dist-info/WHEEL
awslimitchecker-12.0.0.dist-info/entry_points.txt
awslimitchecker-12.0.0.dist-info/top_level.txt
awslimitchecker-12.0.0.dist-info/RECORD
