Metadata-Version: 2.1
Name: awslimitchecker
Version: 12.0.0
Summary: A script and python module to check your AWS service limits and usage, and warn when usage approaches limits.
Home-page: https://github.com/jantman/awslimitchecker
Author: Jason Antman
Author-email: jason@jasonantman.com
License: UNKNOWN
Keywords: AWS EC2 Amazon boto boto3 limits cloud
Platform: UNKNOWN
Classifier: Development Status :: 6 - Mature
Classifier: Environment :: Console
Classifier: Intended Audience :: Developers
Classifier: Intended Audience :: Information Technology
Classifier: Intended Audience :: System Administrators
Classifier: License :: OSI Approved :: GNU Affero General Public License v3 or later (AGPLv3+)
Classifier: Natural Language :: English
Classifier: Operating System :: OS Independent
Classifier: Programming Language :: Python
Classifier: Programming Language :: Python :: 3
Classifier: Programming Language :: Python :: 3.5
Classifier: Programming Language :: Python :: 3.6
Classifier: Programming Language :: Python :: 3.7
Classifier: Programming Language :: Python :: 3.8
Classifier: Topic :: Internet
Classifier: Topic :: System :: Monitoring
Requires-Dist: boto3 (>=1.9.175)
Requires-Dist: botocore
Requires-Dist: termcolor (>=1.1.0)
Requires-Dist: python-dateutil
Requires-Dist: versionfinder (>=0.1.1)
Requires-Dist: pytz
Requires-Dist: urllib3
